sqlite_fts4/__init__.py
sqlite_fts4-1.0.2.dist-info/LICENSE
sqlite_fts4-1.0.2.dist-info/METADATA
sqlite_fts4-1.0.2.dist-info/WHEEL
sqlite_fts4-1.0.2.dist-info/top_level.txt
sqlite_fts4-1.0.2.dist-info/RECORD
