Metadata-Version: 2.1
Name: sqlite-fts4
Version: 1.0.2
Summary: Python functions for working with SQLite FTS4 search
Home-page: https://github.com/simonw/sqlite-fts4
Author: Simon Willison
License: Apache License, Version 2.0
Project-URL: Issues, https://github.com/simonw/sqlite-fts4/issues
Project-URL: CI, https://github.com/simonw/sqlite-fts4/actions
Project-URL: Changelog, https://github.com/simonw/sqlite-fts4/releases
Platform: UNKNOWN
License-File: LICENSE
Provides-Extra: test
Requires-Dist: pytest ; extra == 'test'
